{
    "os": "Windows-10-10.0.19041-SP0",
    "python": "3.7.9",
    "heartbeatAt": "2022-02-09T08:53:58.185395",
    "startedAt": "2022-02-09T08:53:55.072751",
    "docker": null,
    "gpu": "NVIDIA GeForce RTX 3090",
    "gpu_count": 1,
    "cpu_count": 16,
    "cuda": null,
    "args": [],
    "state": "running",
    "program": "E:/projects/DIMO_ObjectDetection/main.py",
    "codePath": "main.py",
    "git": {
        "remote": "https://github.com/EDM-Research/DIMO_ObjectDetection.git",
        "commit": "9350f34441eb46b3856da7d6866b58f5ecf9cd53"
    },
    "email": "steven.moonen@uhasselt.be",
    "root": "E:/projects/DIMO_ObjectDetection",
    "host": "DESKTOP-I544OI6",
    "username": "nmichiels",
    "executable": "E:\\projects\\DIMO_ObjectDetection\\venv\\Scripts\\python.exe"
}
